[{"line":2,"elements":[{"line":4,"name":"landing page","description":"","type":"background","keyword":"Background","steps":[{"result":{"duration":11517772700,"status":"passed"},"line":5,"name":"a user is on the website home page","match":{"location":"com.automation.StepDefinition.AddRemoveElements.a_user_is_on_the_website_home_page()"},"keyword":"Given "}]},{"start_timestamp":"2023-06-15T10:09:35.951Z","line":7,"name":"Add and remove an element","description":"","id":"add-and-remove-an-element;add-and-remove-an-element","type":"scenario","keyword":"Scenario Outline","steps":[{"result":{"duration":439833200,"status":"passed"},"line":8,"name":"the user clicks on the AddRemoveElements on the website","match":{"location":"com.automation.StepDefinition.AddRemoveElements.the_user_clicks_on_the_AddRemoveElements_on_the_website()"},"keyword":"When "},{"result":{"duration":255109400,"status":"passed"},"line":9,"name":"the user clicks on the button AddElement","match":{"location":"com.automation.StepDefinition.AddRemoveElements.the_user_clicks_on_the_button_AddElement()"},"keyword":"And "},{"result":{"duration":2080351400,"status":"passed"},"line":10,"name":"the button Delete is displayed","match":{"location":"com.automation.StepDefinition.AddRemoveElements.the_button_Delete_is_displayed()"},"keyword":"Then "},{"result":{"duration":238126000,"status":"passed"},"line":12,"name":"the user clicks on the button Delete","match":{"location":"com.automation.StepDefinition.AddRemoveElements.the_user_clicks_on_the_button_Delete()"},"keyword":"And "}],"tags":[{"name":"@add_and_remove_element"}]}],"name":"Add and remove an element","description":"","id":"add-and-remove-an-element","keyword":"Feature","uri":"file:src/test/java/com/automation/Features/AddRemoveElements.feature","tags":[{"name":"@add_and_remove_element","type":"Tag","location":{"line":1,"column":1}}]}]